jolt_docker/__init__.py
jolt_docker/__main__.py
jolt_docker/version.py
jolt_docker/version_utils.py
jolt_docker-0.9.452.dist-info/METADATA
jolt_docker-0.9.452.dist-info/WHEEL
jolt_docker-0.9.452.dist-info/entry_points.txt
jolt_docker-0.9.452.dist-info/top_level.txt
jolt_docker-0.9.452.dist-info/RECORD
